Workbook

Sheet Cover
B4: GPW CNC Cost Model 2026
B5: Mexico vs U.S. CNC Manufacturing — Total Landed Cost
B7: How to use this model
B8: 1. Open the "Inputs" sheet. Edit only the cells highlighted in coral — they all feed live formulas, so every output recalculates as you type. Gray cells are computed helpers; do not edit them. 2. Start with the three coral cells that matter most: your part-complexity mix (Tier A/B/C share) and your annual CNC spend. Then refine the wage, shop-rate, overhead, material and freight assumptions to your own situation if you want. 3. Open "Tier Analysis" to see your computed net landed savings by part complexity, and the labor-cost convergence that drives it. 4. Open "Sources" for a citation link and access date for every datapoint. Tip: the Tier A/B/C shares must add to 100% — a check cell on the Inputs sheet flags it in red if they do not.
B17: Headline: up to ~80% on labor and 25–45% on total landed cost vs U.S. domestic — about 27% on a typical OEM part mix (the model computes your exact figure).
B20: Updated June 12, 2026 · Quarterly refresh planned · Tariff figures are volatile — see note on the Inputs sheet
B22: Global Precision Works (GPW) Monterrey, Nuevo León, Mexico sales@gpw-solutions.com https://gpw-solutions.com

Sheet Inputs
B1: Input | C1: Value | D1: Unit | E1: Source / note
B2: Edit only the coral cells — they all feed live formulas. Gray cells are reference only. Defaults reflect Q2 2026 published data.
B4: U.S. CNC LABOR (BLS OEWS May 2025 + ECEC Dec 2025)
B5: CNC Tool Operator — median wage | C5: 24.37 | D5: USD/hr | E5: BLS OEWS May 2025, SOC 51-9161
B6: Machinist — median wage | C6: 28.24 | D6: USD/hr | E6: BLS OEWS May 2025, SOC 51-4041 (reference)
B7: Industrial Engineer — median wage | C7: 49.25 | D7: USD/hr | E7: BLS OEWS May 2025, SOC 17-2112
B8: Benefits load multiplier (×wages) | C8: 1.426 | D8: multiplier | E8: BLS ECEC Dec 2025: benefits = 29.9% of total comp (all-private-industry; conservative proxy — manufacturing runs ~31–32%)
B10: MEXICO CNC LABOR (Tetakawi 2026 benchmark, fully fringed)
B11: Semi-skilled CNC operator | C11: 6.82 | D11: USD/hr | E11: Tetakawi 2026 Wage Benchmark (accessed Jun 2026)
B12: Manufacturing engineer | C12: 23.42 | D12: USD/hr | E12: Tetakawi 2026 Wage Benchmark (accessed Jun 2026)
B13: Entry-level operator | C13: 5.56 | D13: USD/hr | E13: Tetakawi 2026 (reference only)
B15: SAVINGS DRIVERS (MX vs U.S.)
B16: Overhead / indirect savings | C16: 0.2 | D16: ratio | E16: GPW conservative estimate — facility, utilities, indirect & engineering labor cheaper in MX; machine capital & tooling at parity
B17: Material cost (MX ÷ US) | C17: 1 | D17: ratio | E17: ±5% on common metals; +5–15% on specialty alloys (1.00 = parity)
B18: U.S. CNC shop loaded rate (cross-check) | C18: 90 | D18: USD/hr | E18: NTMA/PMA member surveys, range $80–$140
B19: Mexico CNC shop loaded rate (cross-check) | C19: 60 | D19: USD/hr | E19: GPW network benchmark, range $45–$80
B21: PART-COST COMPOSITION BY TIER (each row must sum to 100%)
B22: Tier | C22: Direct labor | D22: Overhead | E22: Material
B23: A — simple, material-heavy | C23: 0.15 | D23: 0.25 | E23: 0.6 | F23: =IF(ABS(C23+D23+E23-1)<0.005,"✓ 100%","⚠ "&TEXT((C23+D23+E23),"0%"))
B24: B — medium, multi-setup | C24: 0.28 | D24: 0.3 | E24: 0.42 | F24: =IF(ABS(C24+D24+E24-1)<0.005,"✓ 100%","⚠ "&TEXT((C24+D24+E24),"0%"))
B25: C — complex, 5-axis / tight tol. | C25: 0.46 | D25: 0.32 | E25: 0.22 | F25: =IF(ABS(C25+D25+E25-1)<0.005,"✓ 100%","⚠ "&TEXT((C25+D25+E25),"0%"))
B26: Composition = how a typical part of that tier breaks down by cost element. Anchored to BLS/BCG machining cost structure; edit to your parts.
B28: LANDED-COST ADDERS (overland freight, USMCA in-house)
B29: Overland freight per part (incremental) | C29: 1 | D29: USD/part | E29: C.H. Robinson + USDA overland freight data 2025 — order-of-magnitude; varies by part size/density/load fill
B30: Customs broker per shipment | C30: 100 | D30: USD/shipment | E30: CBP / industry standard $75–$150 (excludes govt MPF & duties)
B31: Avg parts per shipment | C31: 100 | D31: parts | E31: Adjust to your typical order quantity
B32: Inventory carry per part (incremental) | C32: 0.5 | D32: USD/part | E32: Negligible for most cases
B33: Avg part unit price | C33: 100 | D33: USD/part | E33: Used to express the adders as a % of part cost — edit to your typical unit price
B34: USMCA filing cost | C34: 0 | D34: USD/shipment | E34: Handled in-house (no incremental cost)
B36: TARIFF SCENARIO (optional — only when comparing vs an OFFSHORE origin)
B37: USMCA preferential rate (MX-origin, qualifying) | C37: 0 | D37: % | E37: USTR / CBP — 0% requires meeting USMCA rules of origin (HTSUS Gen. Note 11)
B38: China stack on machined metal parts | C38: 0.35 | D38: % | E38: Sec 301 25% + Sec 122 10% ≈ 35%; +Sec 232 50% on steel/alu content. Post-IEEPA (SCOTUS Feb 2026). VOLATILE — verify before quoting
B39: U.S. domestic baseline | C39: 0 | D39: % | E39: No tariff (domestic supply)
B41: YOUR PORTFOLIO
B42: Tier A (simple) share of spend | C42: 0.25 | D42: % of spend | E42: Default: typical OEM mix
B43: Tier B (medium) share of spend | C43: 0.5 | D43: % of spend | E43: Default: typical OEM mix
B44: Tier C (complex) share of spend | C44: 0.25 | D44: % of spend | E44: Default: typical OEM mix
B45: Shares total (must = 100%) | C45: =C42+C43+C44 | D45: % | E45: =IF(ABS(C45-1)<0.005,"✓ OK","⚠ Adjust shares to total 100%")
B46: Annual CNC machining spend | C46: 500000 | D46: USD | E46: Edit to your actual annual spend

Sheet Tier Analysis
B1: Tier | C1: Part-cost savings | D1: Less landed adders | E1: Net landed savings | F1: Your spend | G1: Your savings
B2: Your Total Landed Cost Savings by Part Complexity
B3: Every figure below is computed live from the Inputs sheet. Change your mix and spend (Inputs) and these update.
B5: Tier | C5: Part-cost savings | D5: Less landed adders | E5: Net landed savings | F5: Your spend | G5: Your savings
B6: A — simple, material-heavy | C6: =Inputs!C23*$G$18 + Inputs!D23*Inputs!C16 + Inputs!E23*(1-Inputs!C17) | D6: =$G$21 | E6: =C6-D6 | F6: =Inputs!C46*Inputs!C42 | G6: =F6*E6
B7: B — medium, multi-setup | C7: =Inputs!C24*$G$18 + Inputs!D24*Inputs!C16 + Inputs!E24*(1-Inputs!C17) | D7: =$G$21 | E7: =C7-D7 | F7: =Inputs!C46*Inputs!C43 | G7: =F7*E7
B8: C — complex, 5-axis / tight tol. | C8: =Inputs!C25*$G$18 + Inputs!D25*Inputs!C16 + Inputs!E25*(1-Inputs!C17) | D8: =$G$21 | E8: =C8-D8 | F8: =Inputs!C46*Inputs!C44 | G8: =F8*E8
B10: WEIGHTED TOTAL (your portfolio) | F10: =SUM(F6:F8) | G10: =SUM(G6:G8)
B11: Weighted net landed savings (% of spend) | F11: =G10/F10
B13: Methodology: Part-cost savings = (direct-labor share × labor savings) + (overhead share × overhead savings) + (material share × material savings), per the composition on the Inputs sheet. Net landed savings then subtracts overland freight, brokerage and inventory carry expressed as a % of average part price. Conservative by design — it does not include any tariff advantage vs U.S. domestic (USMCA = 0% either way).
B16: Labor Cost Convergence (drives the direct-labor savings above)
B17: Role | C17: U.S. wage (BLS) | D17: U.S. fully-loaded | E17: MX fully-fringed | F17: MX as % of US | G17: Labor savings
B18: CNC Operator (production) | C18: =Inputs!C5 | D18: =Inputs!C5*Inputs!C8 | E18: =Inputs!C11 | F18: =E18/D18 | G18: =1-F18
B19: Manufacturing Engineer (context) | C19: =Inputs!C7 | D19: =Inputs!C7*Inputs!C8 | E19: =Inputs!C12 | F19: =E19/D19 | G19: =1-F19
B20: The model uses the CNC-operator saving (the direct production labor in a machined part) as its direct-labor driver. Engineering/indirect labor (shown for context, ~67% cheaper) is captured in the lower "overhead savings" assumption, not the direct-labor line.
F21: Landed adder %: | G21: =(Inputs!C29 + (Inputs!C30+Inputs!C34)/Inputs!C31 + Inputs!C32)/Inputs!C33
B22: Landed adders as % of avg part price | F22: Shop-rate cross-check: | G22: =1-Inputs!C19/Inputs!C18
B24: Tariff Differential (optional — only when comparing vs an OFFSHORE origin)
B25: Duty avoided vs China-origin (on the dutiable part value) | G25: =Inputs!C38-Inputs!C37
B26: Duty advantage vs U.S. domestic (none — both 0%) | G26: =Inputs!C37-Inputs!C39
B27: Shown separately because a tariff advantage exists only against offshore (e.g., China) supply, not against U.S. domestic. The net landed savings above deliberately exclude it. Tariff figures are post-IEEPA (SCOTUS Feb 2026) and volatile — verify the China stack before quoting.

Sheet Sources
B1: ID | C1: Source | D1: URL | E1: Used in
B2: Sources Used in This Model
B3: Accessed June 2026. Quarterly refresh planned. Tariff figures are volatile (post-IEEPA) — re-verify before quoting.
B5: ID | C5: Source | D5: URL | E5: Used in
B6: BLS-1 | C6: BLS OEWS May 2025 — National occupational wages | D6: https://www.bls.gov/oes/current/oes_nat.htm | E6: U.S. wages
B7: BLS-2 | C7: BLS Employer Costs for Employee Compensation (Dec 2025) | D7: https://www.bls.gov/news.release/ecec.htm | E7: Fully-loaded multiplier
B8: MX-1 | C8: Tetakawi Manufacturing Wages in Mexico 2026 benchmark | D8: https://insights.tetakawi.com/manufacturing-wages-in-mexico-2025-2026-executive-benchmark-guide | E8: Mexico wages
B9: Cost-1 | C9: BCG: Shifting Dynamics of Nearshoring in Mexico (2024) | D9: https://www.bcg.com/publications/2024/shifting-dynamics-of-nearshoring-in-mexico | E9: Cost composition
B10: Cost-2 | C10: Reshoring Initiative TCO Estimator framework | D10: https://www.reshorenow.org/tco-estimator/ | E10: TCO methodology
B11: Resh-1 | C11: Reshoring Initiative 2024 Annual Report | D11: https://reshorenow.org/june-9-2025/ | E11: Reshoring trends
B12: Resh-2 | C12: Kearney 2025 Reshoring Index | D12: https://www.kearney.com/service/operations-performance/us-reshoring-index | E12: Wage convergence
B13: Trade-1 | C13: USTR Section 301 enforcement actions | D13: https://ustr.gov/issue-areas/enforcement/section-301-investigations | E13: Tariff scenario
B14: Trade-2 | C14: CBP — USMCA (rules of origin, duty-free) | D14: https://www.cbp.gov/trade/usmca | E14: USMCA filing
B15: Trade-3 | C15: CBP — Section 232 steel/aluminum tariffs FAQ | D15: https://www.cbp.gov/trade/programs-administration/entry-summary/232-tariffs-aluminum-and-steel-faqs | E15: Tariff scenario
B16: Freight-1 | C16: C.H. Robinson North America Freight Market Update, April 2025 | D16: https://www.chrobinson.com/en-us/resources/insights-and-advisories/north-america-freight-insights/apr-2025-freight-market-update/addl-supply-chain-updates/cross-border/ | E16: Overland freight (qualitative)
B17: Freight-2 | C17: CBP — Customs broker user fees | D17: https://www.cbp.gov/trade/programs-administration/customs-brokers/fees | E17: Brokerage
